adapt/__init__.py
adapt/alignment.py
adapt/coverage_analysis.py
adapt/guide_search.py
adapt/primer_search.py
adapt/target_search.py
adapt/models/classify/cas13a/v1_0/saved_model.pb
adapt/models/classify/cas13a/v1_0/assets.extra/context_nt.arg
adapt/models/classify/cas13a/v1_0/assets.extra/default_threshold.arg
adapt/models/classify/cas13a/v1_0/assets.extra/guide_length.arg
adapt/models/classify/cas13a/v1_0/variables/variables.data-00000-of-00001
adapt/models/classify/cas13a/v1_0/variables/variables.index
adapt/models/regress/cas13a/v1_0/saved_model.pb
adapt/models/regress/cas13a/v1_0/assets.extra/context_nt.arg
adapt/models/regress/cas13a/v1_0/assets.extra/default_threshold.arg
adapt/models/regress/cas13a/v1_0/assets.extra/guide_length.arg
adapt/models/regress/cas13a/v1_0/variables/variables.data-00000-of-00001
adapt/models/regress/cas13a/v1_0/variables/variables.index
adapt/prepare/__init__.py
adapt/prepare/align.py
adapt/prepare/cluster.py
adapt/prepare/ncbi_neighbors.py
adapt/prepare/prepare_alignment.py
adapt/prepare/tests/__init__.py
adapt/prepare/tests/test_align.py
adapt/prepare/tests/test_cluster.py
adapt/prepare/tests/test_ncbi_neighbors.py
adapt/specificity/__init__.py
adapt/specificity/alignment_query.py
adapt/specificity/kmer_leaf.py
adapt/specificity/kmer_shard.py
adapt/specificity/tests/__init__.py
adapt/specificity/tests/test_alignment_query.py
adapt/specificity/tests/test_kmer_leaf.py
adapt/specificity/tests/test_kmer_shard.py
adapt/tests/__init__.py
adapt/tests/test_alignment.py
adapt/tests/test_coverage_analysis.py
adapt/tests/test_guide_search.py
adapt/tests/test_primer_search.py
adapt/tests/test_target_search.py
adapt/utils/__init__.py
adapt/utils/formatting.py
adapt/utils/index_compress.py
adapt/utils/log.py
adapt/utils/lsh.py
adapt/utils/mutate.py
adapt/utils/oligo.py
adapt/utils/predict_activity.py
adapt/utils/search.py
adapt/utils/seq_io.py
adapt/utils/thermo.py
adapt/utils/trie.py
adapt/utils/version.py
adapt/utils/weight.py
adapt_diagnostics-1.6.0.dist-info/LICENSE
adapt_diagnostics-1.6.0.dist-info/METADATA
adapt_diagnostics-1.6.0.dist-info/WHEEL
adapt_diagnostics-1.6.0.dist-info/top_level.txt
adapt_diagnostics-1.6.0.dist-info/RECORD
