Metadata-Version: 2.1
Name: adapt-diagnostics
Version: 1.6.0
Summary: Tools to design guides for diagnostics
Home-page: https://github.com/broadinstitute/adapt
Author: Hayden Metsky
Author-email: hmetsky@broadinstitute.org
Maintainer: Priya P. Pillai
Maintainer-email: ppillai@broadinstitute.org
Classifier: Programming Language :: Python :: 3
Classifier: License :: OSI Approved :: MIT License
Classifier: Operating System :: OS Independent
License-File: LICENSE
Requires-Dist: numpy (<1.19.0,>=1.16.0)
Requires-Dist: scipy (==1.4.1)
Requires-Dist: tensorflow (==2.3.2)
Provides-Extra: aws
Requires-Dist: boto3 (>=1.14.54) ; extra == 'aws'
Requires-Dist: botocore (>=1.17.54) ; extra == 'aws'
Provides-Extra: thermo
Requires-Dist: primer3-py (==0.6.1) ; extra == 'thermo'
